airflow_secret_loader/__init__.py
airflow_secret_loader/loader.py
airflow_secret_loader-1.1.0.dist-info/METADATA
airflow_secret_loader-1.1.0.dist-info/WHEEL
airflow_secret_loader-1.1.0.dist-info/top_level.txt
airflow_secret_loader-1.1.0.dist-info/RECORD
