Metadata-Version: 2.4
Name: airflow-secret-loader
Version: 1.1.0
Summary: Fetch AWS secrets as dictionary using optional Azure Identity role assumption
Home-page: https://github.com/rajeshkbathula/airflow-secret-loader
Author: rajeshkbathula
Author-email: rajb7723@gmail.com
Project-URL: Source Code, https://github.com/rajeshkbathula/airflow-secret-loader
Project-URL: Bug Tracker, https://github.com/rajeshkbathula/airflow-secret-loader/issues
Classifier: Programming Language :: Python :: 3
Classifier: Operating System :: OS Independent
Requires-Python: >=3.6
Requires-Dist: boto3
Requires-Dist: azure-identity
Dynamic: author
Dynamic: author-email
Dynamic: classifier
Dynamic: description
Dynamic: description-content-type
Dynamic: home-page
Dynamic: project-url
Dynamic: requires-dist
Dynamic: requires-python
Dynamic: summary
